peppers/.fake_helper.py.un~
peppers/.log_helper.py.un~
peppers/.random_helper.py.un~
peppers/.uri_helper.py.un~
peppers/__init__.py
peppers/log_helper.py
peppers/num_str_helper.py
peppers/random_helper.py
peppers/sys_helper.py
peppers/time_helper.py
peppers/uri_helper.py
peppers-0.1.1.dist-info/LICENSE
peppers-0.1.1.dist-info/WHEEL
peppers-0.1.1.dist-info/METADATA
peppers-0.1.1.dist-info/RECORD
