Metadata-Version: 2.1
Name: peppers
Version: 0.1.1
Summary: peppers for soup? Pyppers for Python!
Author: innerNULL
Requires-Python: >=3.7,<4.0
Classifier: Programming Language :: Python :: 3
Classifier: Programming Language :: Python :: 3.7
Classifier: Programming Language :: Python :: 3.8
Classifier: Programming Language :: Python :: 3.9
